notebook_gena/__init__.py
notebook_gena/foo.py
notebook_gena-1.0.0.dist-info/LICENSE
notebook_gena-1.0.0.dist-info/METADATA
notebook_gena-1.0.0.dist-info/WHEEL
notebook_gena-1.0.0.dist-info/top_level.txt
notebook_gena-1.0.0.dist-info/RECORD
