Metadata-Version: 2.2
Name: notebook-gena
Version: 1.0.0
Summary: This is a template repository for Python projects that use uv for their dependency management.
Author-email: Rajesh Rao <rao.rajesh8@gmail.com>
Project-URL: Homepage, https://rajeshpv.github.io/notebook-gena/
Project-URL: Repository, https://github.com/rajeshpv/notebook-gena
Project-URL: Documentation, https://rajeshpv.github.io/notebook-gena/
Keywords: python
Classifier: Intended Audience :: Developers
Classifier: Programming Language :: Python
Classifier: Programming Language :: Python :: 3
Classifier: Programming Language :: Python :: 3.9
Classifier: Programming Language :: Python :: 3.10
Classifier: Programming Language :: Python :: 3.11
Classifier: Programming Language :: Python :: 3.12
Classifier: Programming Language :: Python :: 3.13
Classifier: Topic :: Software Development :: Libraries :: Python Modules
Requires-Python: <4.0,>=3.9
License-File: LICENSE
